setup.py
eqres/__init__.py
eqres/error_code.py
eqres/response.py
eqres.egg-info/PKG-INFO
eqres.egg-info/SOURCES.txt
eqres.egg-info/dependency_links.txt
eqres.egg-info/top_level.txt